odoo/addons/intrastat_product_hscodes_import/README.rst
odoo/addons/intrastat_product_hscodes_import/__init__.py
odoo/addons/intrastat_product_hscodes_import/__manifest__.py
odoo/addons/intrastat_product_hscodes_import/i18n/es.po
odoo/addons/intrastat_product_hscodes_import/i18n/fr.po
odoo/addons/intrastat_product_hscodes_import/i18n/intrastat_product_hscodes_import.pot
odoo/addons/intrastat_product_hscodes_import/i18n/it.po
odoo/addons/intrastat_product_hscodes_import/readme/CONTRIBUTORS.md
odoo/addons/intrastat_product_hscodes_import/readme/DESCRIPTION.md
odoo/addons/intrastat_product_hscodes_import/readme/USAGE.md
odoo/addons/intrastat_product_hscodes_import/security/ir.model.access.csv
odoo/addons/intrastat_product_hscodes_import/static/data/2023_de_intrastat_codes.csv
odoo/addons/intrastat_product_hscodes_import/static/data/2023_en_intrastat_codes.csv
odoo/addons/intrastat_product_hscodes_import/static/data/2023_fr_intrastat_codes.csv
odoo/addons/intrastat_product_hscodes_import/static/data/2023_nl_intrastat_codes.csv
odoo/addons/intrastat_product_hscodes_import/static/description/icon.png
odoo/addons/intrastat_product_hscodes_import/static/description/index.html
odoo/addons/intrastat_product_hscodes_import/static/description/installer_todo_example.png
odoo/addons/intrastat_product_hscodes_import/wizards/__init__.py
odoo/addons/intrastat_product_hscodes_import/wizards/intrastat_hscodes_import_installer.py
odoo/addons/intrastat_product_hscodes_import/wizards/intrastat_hscodes_import_installer_views.xml
odoo_addon_intrastat_product_hscodes_import-17.0.1.0.0.5.dist-info/METADATA
odoo_addon_intrastat_product_hscodes_import-17.0.1.0.0.5.dist-info/WHEEL
odoo_addon_intrastat_product_hscodes_import-17.0.1.0.0.5.dist-info/top_level.txt
odoo_addon_intrastat_product_hscodes_import-17.0.1.0.0.5.dist-info/RECORD
